AzureDevOpsFlow/ExampleConfig.json
AzureDevOpsFlow/WorkItem.py
AzureDevOpsFlow/WorkItemService.py
AzureDevOpsFlow/__init__.py
AzureDevOpsFlow/main.py
azuredevopsflow-0.9.3.dist-info/LICENSE
azuredevopsflow-0.9.3.dist-info/METADATA
azuredevopsflow-0.9.3.dist-info/WHEEL
azuredevopsflow-0.9.3.dist-info/entry_points.txt
azuredevopsflow-0.9.3.dist-info/top_level.txt
azuredevopsflow-0.9.3.dist-info/RECORD
