Metadata-Version: 2.1
Name: azuredevopsflow
Version: 0.9.3
Summary: A package to generate flow metrics charts and run Monte Carlo Simulation based Forecasts based on WIQL queries against Azure DevOps.
Home-page: https://letpeople.work
Author: Benjamin Huser-Berta
Author-email: benj.huser@gmail.com
Classifier: Programming Language :: Python :: 3
Classifier: License :: OSI Approved :: MIT License
Classifier: Operating System :: OS Independent
Requires-Python: >=3.6
License-File: LICENSE
Requires-Dist: argparse
Requires-Dist: azure-devops
Requires-Dist: flowmetricscsv
Requires-Dist: montecarlocsv
